AEIporter/AEIporter.py
AEIporter/__init__.py
AEIporter-2024.8.3.dist-info/LICENSE
AEIporter-2024.8.3.dist-info/METADATA
AEIporter-2024.8.3.dist-info/WHEEL
AEIporter-2024.8.3.dist-info/entry_points.txt
AEIporter-2024.8.3.dist-info/top_level.txt
AEIporter-2024.8.3.dist-info/RECORD
